LICENSE
MANIFEST.in
NOTICE
README.md
pyproject.toml
setup.py
himap/__init__.py
himap/ab.py
himap/base.py
himap/main.py
himap/plot.py
himap/test_RUL.py
himap/test_pi.py
himap/utils.py
himap.egg-info/PKG-INFO
himap.egg-info/SOURCES.txt
himap.egg-info/dependency_links.txt
himap.egg-info/requires.txt
himap.egg-info/top_level.txt
himap/cython_build/fwd_bwd.c
himap/cython_build/__init__.py
himap/cython_build/fwd_bwd.c
himap/cython_build/fwd_bwd.pyx
himap/example_data/test_FD001_disc_20_mod.csv
himap/example_data/train_FD001_disc_20_mod.csv
tests/test_base_unittest.py
tests/test_hmm_integration_cmapss.py
tests/test_hsmm_smoke_cmapss.py
tests/test_utils_unit.py