Metadata-Version: 2.4
Name: himap
Version: 1.3.0
Summary: HiMAP: Hidden Markov models for Advanced Prognostics!
Author-email: Thanos Kontogiannis <a.kontogiannis@tudelft.nl>, Mariana Salinas-Camus <m.salinascamus@tudelft.nl>, Nick Eleftheroglou <n.eleftheroglou@tudelft.nl>
Maintainer-email: Thanos Kontogiannis <a.kontogiannis@tudelft.nl>, Mariana Salinas-Camus <m.salinascamus@tudelft.nl>
License-Expression: Apache-2.0
Project-URL: Documentation, https://himap.readthedocs.io/en/latest/
Project-URL: Repository, https://github.com/GroupiSP/himap/
Keywords: Hidden Markov Models,Prognostics
Classifier: Development Status :: 5 - Production/Stable
Classifier: Programming Language :: Python
Classifier: Programming Language :: Python :: 3 :: Only
Classifier: Programming Language :: Python :: 3.9
Classifier: Programming Language :: Python :: 3.10
Classifier: Programming Language :: Python :: 3.11
Classifier: Programming Language :: Python :: 3.12
Requires-Python: <3.13,>=3.9
License-File: LICENSE
Requires-Dist: matplotlib>=3.7.1
Requires-Dist: numpy>=1.23.5
Requires-Dist: scikit_learn>=1.3.0
Requires-Dist: scipy>=1.10.0
Requires-Dist: tqdm>=4.65.0
Requires-Dist: numba>=0.60
Requires-Dist: pandas>=1.5.3
Requires-Dist: Cython>=0.29.35
Provides-Extra: test
Requires-Dist: pytest>=8.0; extra == "test"
Dynamic: license-file
